fedflow/__init__.py
fedflow/__main__.py
fedflow/config.py
fedflow/context.py
fedflow/detect.py
fedflow/fedflow.py
fedflow/units.py
fedflow/core/__init__.py
fedflow/core/message.py
fedflow/core/scheduler.py
fedflow/core/task.py
fedflow/core/taskgroup.py
fedflow/mail/__init__.py
fedflow/mail/mail.py
fedflow/mail/send_mail.py
fedflow/mail/templates.py
fedflow/resources/config.yaml
fedflow/resources/logging.yaml
fedflow/utils/__init__.py
fedflow/utils/module_utils.py
fedflow/utils/data/__init__.py
fedflow/utils/data/dirichlet_split.py
fedflow/utils/data/label_split.py
fedflow/utils/data/split.py
fedflow/utils/trainer/__init__.py
fedflow/utils/trainer/supervised_trainer.py
fedflow-0.2.1.dist-info/LICENSE
fedflow-0.2.1.dist-info/METADATA
fedflow-0.2.1.dist-info/WHEEL
fedflow-0.2.1.dist-info/top_level.txt
fedflow-0.2.1.dist-info/RECORD
