Metadata-Version: 2.1
Name: fedflow
Version: 0.2.1
Summary: auto-scheduler for pytorch task.
Home-page: https://github.com/malanore-z/fedflow
Author: malanore
Author-email: malanore.z@gmail.com
License: UNKNOWN
Project-URL: Bug Tracker, https://github.com/malanore-z/fedflow/issues
Platform: UNKNOWN
Classifier: Intended Audience :: Developers
Classifier: Programming Language :: Python :: 3
Classifier: License :: OSI Approved :: MIT License
Classifier: Operating System :: OS Independent
Requires-Python: >=3.4
License-File: LICENSE
Requires-Dist: ngpuinfo (==0.1.0)
Requires-Dist: psutil
Requires-Dist: PyYAML
Requires-Dist: numpy
Requires-Dist: matplotlib
